<!--Copyright 2012 MLB Advanced Media, L.P.  Use of any content on this page acknowledges agreement to the terms posted here http://gdx.mlb.com/components/copyright.txt--><inning num="12" away_team="bal" home_team="kca" next="Y"><top><atbat num="90" b="0" s="0" o="1" start_tfs="231953" start_tfs_zulu="2012-05-17T03:19:53Z" batter="542897" stand="L" b_height="6-0" pitcher="502264" p_throws="R" des="Xavier Avery bunt pops out to catcher Humberto Quintero.  " event="Bunt Pop Out"><pitch des="In play, out(s)" id="686" type="X" tfs="232029" tfs_zulu="2012-05-17T03:20:29Z" x="96.14" y="159.74" sv_id="120516_222007" start_speed="90.6" end_speed="82.2" sz_top="3.42" sz_bot="1.65" pfx_x="-10.29" pfx_z="4.29" px="0.155" pz="1.971" x0="-2.499" y0="50.0" z0="6.202" vx0="10.33" vy0="-132.287" vz0="-6.211" ax="-17.892" ay="33.058" az="-24.644" break_y="23.7" break_angle="30.6" break_length="7.1" pitch_type="SI" type_confidence=".905" zone="8" nasty="48" spin_dir="247.175" spin_rate="2128.897"  cc="" mt=""/></atbat><atbat num="91" b="0" s="1" o="1" start_tfs="232039" start_tfs_zulu="2012-05-17T03:20:39Z" batter="429666" stand="R" b_height="6-1" pitcher="502264" p_throws="R" des="J.   Hardy singles on a ground ball to shortstop Alcides Escobar.  " event="Single"><pitch des="Called Strike" id="690" type="S" tfs="232040" tfs_zulu="2012-05-17T03:20:40Z" x="117.60" y="159.74" sv_id="120516_222040" start_speed="91.0" end_speed="82.2" sz_top="3.08" sz_bot="1.48" pfx_x="-9.39" pfx_z="4.15" px="-0.542" pz="1.948" x0="-2.524" y0="50.0" z0="6.164" vx0="8.309" vy0="-133.13" vz0="-6.183" ax="-16.412" ay="35.467" az="-24.836" break_y="23.7" break_angle="28.4" break_length="7.0" pitch_type="SI" type_confidence=".902" zone="7" nasty="57" spin_dir="245.910" spin_rate="1959.124"  cc="" mt=""/><pitch des="In play, no out" id="691" type="X" tfs="232120" tfs_zulu="2012-05-17T03:21:20Z" x="94.42" y="160.60" sv_id="120516_222053" start_speed="91.7" end_speed="82.7" sz_top="3.38" sz_bot="1.52" pfx_x="-11.26" pfx_z="3.91" px="0.209" pz="1.952" x0="-2.567" y0="50.0" z0="6.152" vx0="11.071" vy0="-133.908" vz0="-6.176" ax="-19.926" ay="35.654" az="-25.169" break_y="23.7" break_angle="32.6" break_length="7.3" pitch_type="SI" type_confidence=".907" zone="8" nasty="41" spin_dir="250.630" spin_rate="2288.334"  cc="" mt=""/><runner id="429666" start="" end="1B" event="Single"/></atbat><atbat num="92" b="2" s="1" o="2" start_tfs="232131" start_tfs_zulu="2012-05-17T03:21:31Z" batter="455976" stand="L" b_height="6-1" pitcher="502264" p_throws="R" des="Nick Markakis flies out to center fielder Jarrod Dyson.    J.   Hardy to 2nd.  " event="Flyout"><pitch des="Ball" id="695" type="B" tfs="232139" tfs_zulu="2012-05-17T03:21:39Z" x="74.68" y="173.55" on_1b="429666" sv_id="120516_222139" start_speed="90.7" end_speed="81.6" sz_top="3.38" sz_bot="1.61" pfx_x="-10.45" pfx_z="5.36" px="0.823" pz="1.351" x0="-2.542" y0="50.0" z0="6.113" vx0="12.162" vy0="-132.251" vz0="-7.844" ax="-17.967" ay="35.876" az="-22.884" break_y="23.6" break_angle="30.7" break_length="6.9" pitch_type="SI" type_confidence=".905" zone="14" nasty="79" spin_dir="242.658" spin_rate="2218.846"  cc="" mt=""/><pitch des="Ball" id="696" type="B" tfs="232203" tfs_zulu="2012-05-17T03:22:03Z" x="67.81" y="149.38" on_1b="429666" sv_id="120516_222203" start_speed="91.8" end_speed="82.6" sz_top="3.37" sz_bot="1.55" pfx_x="-12.93" pfx_z="5.23" px="1.01" pz="2.441" x0="-2.566" y0="50.0" z0="6.204" vx0="13.73" vy0="-133.869" vz0="-5.476" ax="-22.886" ay="35.539" az="-22.839" break_y="23.7" break_angle="38.6" break_length="7.2" pitch_type="SI" type_confidence=".908" zone="14" nasty="54" spin_dir="247.809" spin_rate="2678.621"  cc="Nathan Adcock may prefer to go after Nick Markakis, whose OPS is .742 this season, with the slider rather than facing Adam Jones, whose OPS is .911." mt=""/><pitch des="Called Strike" id="697" type="S" tfs="232235" tfs_zulu="2012-05-17T03:22:35Z" x="109.01" y="154.56" on_1b="429666" sv_id="120516_222236" start_speed="91.4" end_speed="82.8" sz_top="3.34" sz_bot="1.51" pfx_x="-11.08" pfx_z="4.92" px="-0.226" pz="2.17" x0="-2.685" y0="50.0" z0="6.202" vx0="10.181" vy0="-133.534" vz0="-6.063" ax="-19.61" ay="34.145" az="-23.403" break_y="23.7" break_angle="34.5" break_length="7.0" pitch_type="SI" type_confidence=".907" zone="5" nasty="37" spin_dir="245.902" spin_rate="2333.931"  cc="" mt=""/><pitch des="In play, out(s)" id="698" type="X" tfs="232335" tfs_zulu="2012-05-17T03:23:35Z" x="112.45" y="146.79" on_1b="429666" sv_id="120516_222303" start_speed="91.8" end_speed="83.7" sz_top="3.43" sz_bot="1.62" pfx_x="-10.57" pfx_z="7.47" px="-0.337" pz="2.549" x0="-2.679" y0="50.0" z0="6.192" vx0="9.785" vy0="-134.085" vz0="-6.065" ax="-19.052" ay="31.812" az="-18.638" break_y="23.7" break_angle="40.0" break_length="5.9" pitch_type="SI" type_confidence=".907" zone="4" nasty="36" spin_dir="234.606" spin_rate="2528.708"  cc="" mt=""/><runner id="429666" start="1B" end="2B" event="Flyout"/></atbat><atbat num="93" b="0" s="0" o="3" start_tfs="232400" start_tfs_zulu="2012-05-17T03:24:00Z" batter="430945" stand="R" b_height="6-3" pitcher="502264" p_throws="R" des="Adam Jones pops out to third baseman Mike Moustakas in foul territory.  " event="Pop Out"><pitch des="In play, out(s)" id="703" type="X" tfs="232428" tfs_zulu="2012-05-17T03:24:28Z" x="125.32" y="143.33" on_2b="429666" sv_id="120516_222408" start_speed="79.1" end_speed="72.0" sz_top="3.62" sz_bot="1.68" pfx_x="3.58" pfx_z="-0.11" px="-0.733" pz="2.626" x0="-2.686" y0="50.0" z0="6.461" vx0="3.374" vy0="-115.906" vz0="-1.576" ax="4.759" ay="26.33" az="-32.248" break_y="23.7" break_angle="-9.5" break_length="10.1" pitch_type="KC" type_confidence=".888" zone="13" nasty="72" spin_dir="89.109" spin_rate="595.751"  cc="" mt=""/><runner id="429666" start="2B" end="" event="Pop Out"/></atbat></top><bottom><atbat num="94" b="1" s="3" o="1" start_tfs="232632" start_tfs_zulu="2012-05-17T03:26:32Z" batter="279827" stand="R" b_height="5-9" pitcher="445968" p_throws="L" des="Humberto Quintero strikes out swinging.  " event="Strikeout"><pitch des="Ball" id="709" type="B" tfs="232639" tfs_zulu="2012-05-17T03:26:39Z" x="144.21" y="183.05" sv_id="120516_222639" start_speed="82.8" end_speed="75.7" sz_top="3.2" sz_bot="1.6" pfx_x="6.51" pfx_z="5.3" px="-1.269" pz="0.979" x0="1.753" y0="50.0" z0="5.816" vx0="-9.173" vy0="-120.97" vz0="-6.342" ax="9.498" ay="26.991" az="-24.368" break_y="23.7" break_angle="-16.5" break_length="7.5" pitch_type="CH" type_confidence=".896" zone="13" nasty="65" spin_dir="129.416" spin_rate="1474.424"  cc="" mt=""/><pitch des="Foul" id="710" type="S" tfs="232656" tfs_zulu="2012-05-17T03:26:56Z" x="127.04" y="171.83" sv_id="120516_222656" start_speed="87.4" end_speed="79.9" sz_top="3.24" sz_bot="1.5" pfx_x="6.59" pfx_z="3.6" px="-0.768" pz="1.415" x0="1.89" y0="50.0" z0="5.794" vx0="-8.808" vy0="-127.752" vz0="-5.75" ax="10.749" ay="29.669" az="-26.236" break_y="23.7" break_angle="-17.8" break_length="7.2" pitch_type="FT" type_confidence=".559" zone="13" nasty="72" spin_dir="118.918" spin_rate="1394.557"  cc="" mt=""/><pitch des="Foul" id="711" type="S" tfs="232718" tfs_zulu="2012-05-17T03:27:18Z" x="72.96" y="127.79" sv_id="120516_222718" start_speed="83.4" end_speed="75.3" sz_top="3.24" sz_bot="1.5" pfx_x="7.66" pfx_z="5.16" px="0.829" pz="3.325" x0="1.915" y0="50.0" z0="6.001" vx0="-4.96" vy0="-122.203" vz0="-1.265" ax="11.312" ay="29.429" az="-24.488" break_y="23.7" break_angle="-22.3" break_length="7.4" pitch_type="CH" type_confidence=".479" zone="12" nasty="62" spin_dir="124.195" spin_rate="1623.614"  cc="" mt=""/><pitch des="Foul" id="712" type="S" tfs="232746" tfs_zulu="2012-05-17T03:27:46Z" x="91.85" y="146.79" sv_id="120516_222746" start_speed="87.8" end_speed="79.9" sz_top="3.24" sz_bot="1.5" pfx_x="2.59" pfx_z="7.93" px="0.265" pz="2.481" x0="1.71" y0="50.0" z0="5.827" vx0="-4.493" vy0="-128.616" vz0="-4.669" ax="4.274" ay="30.545" az="-19.023" break_y="23.7" break_angle="-9.2" break_length="5.0" pitch_type="FC" type_confidence=".844" zone="6" nasty="31" spin_dir="161.998" spin_rate="1559.801"  cc="" mt=""/><pitch des="Swinging Strike" id="713" type="S" tfs="232826" tfs_zulu="2012-05-17T03:28:26Z" x="124.46" y="183.05" sv_id="120516_222816" start_speed="82.5" end_speed="74.1" sz_top="3.24" sz_bot="1.5" pfx_x="-7.41" pfx_z="-3.99" px="-0.741" pz="0.936" x0="2.005" y0="50.0" z0="5.804" vx0="-4.194" vy0="-120.91" vz0="-3.344" ax="-10.481" ay="33.413" az="-37.735" break_y="23.6" break_angle="16.5" break_length="11.7" pitch_type="SL" type_confidence=".943" zone="13" nasty="40" spin_dir="297.950" spin_rate="1423.654"  cc="" mt=""/></atbat><atbat num="95" b="2" s="3" o="2" start_tfs="232842" start_tfs_zulu="2012-05-17T03:28:42Z" batter="502481" stand="L" b_height="5-9" pitcher="445968" p_throws="L" des="Jarrod Dyson strikes out on foul tip.  " event="Strikeout"><pitch des="Ball" id="717" type="B" tfs="232848" tfs_zulu="2012-05-17T03:28:48Z" x="163.09" y="163.19" sv_id="120516_222849" start_speed="82.7" end_speed="74.8" sz_top="3.39" sz_bot="1.7" pfx_x="-10.48" pfx_z="-1.38" px="-1.909" pz="1.748" x0="1.904" y0="50.0" z0="5.741" vx0="-5.797" vy0="-121.156" vz0="-2.173" ax="-15.017" ay="31.567" az="-34.076" break_y="23.7" break_angle="25.2" break_length="10.9" pitch_type="SL" type_confidence=".950" zone="13" nasty="61" spin_dir="277.219" spin_rate="1812.576"  cc="" mt=""/><pitch des="Ball" id="718" type="B" tfs="232906" tfs_zulu="2012-05-17T03:29:06Z" x="111.59" y="166.65" sv_id="120516_222907" start_speed="82.3" end_speed="74.3" sz_top="3.3" sz_bot="1.65" pfx_x="-6.39" pfx_z="-2.62" px="-0.325" pz="1.612" x0="2.162" y0="50.0" z0="5.754" vx0="-3.901" vy0="-120.675" vz0="-2.084" ax="-9.083" ay="31.297" az="-35.831" break_y="23.7" break_angle="15.3" break_length="10.8" pitch_type="SL" type_confidence=".937" zone="13" nasty="41" spin_dir="291.931" spin_rate="1177.163"  cc="" mt=""/><pitch des="Called Strike" id="719" type="S" tfs="232930" tfs_zulu="2012-05-17T03:29:30Z" x="115.02" y="153.69" sv_id="120516_222930" start_speed="87.7" end_speed="79.5" sz_top="3.41" sz_bot="1.65" pfx_x="-0.02" pfx_z="7.86" px="-0.388" pz="2.141" x0="1.91" y0="50.0" z0="5.732" vx0="-5.768" vy0="-128.384" vz0="-5.185" ax="-0.026" ay="31.875" az="-19.267" break_y="23.7" break_angle="3.9" break_length="5.1" pitch_type="FC" type_confidence=".924" zone="7" nasty="44" spin_dir="180.114" spin_rate="1458.537"  cc="" mt=""/><pitch des="Swinging Strike" id="720" type="S" tfs="232946" tfs_zulu="2012-05-17T03:29:46Z" x="121.89" y="158.88" sv_id="120516_222947" start_speed="87.7" end_speed="79.9" sz_top="3.39" sz_bot="1.58" pfx_x="1.83" pfx_z="2.8" px="-0.652" pz="1.94" x0="1.888" y0="50.0" z0="5.689" vx0="-6.983" vy0="-128.346" vz0="-3.961" ax="2.996" ay="30.967" az="-27.506" break_y="23.7" break_angle="-2.9" break_length="7.1" pitch_type="FC" type_confidence=".689" zone="7" nasty="46" spin_dir="147.308" spin_rate="626.985"  cc="" mt=""/><pitch des="Foul Tip" id="721" type="S" tfs="233017" tfs_zulu="2012-05-17T03:30:17Z" x="106.44" y="174.42" sv_id="120516_223008" start_speed="88.1" end_speed="80.1" sz_top="3.39" sz_bot="1.58" pfx_x="0.29" pfx_z="2.82" px="-0.121" pz="1.254" x0="1.831" y0="50.0" z0="5.668" vx0="-5.019" vy0="-128.993" vz0="-5.701" ax="0.471" ay="32.226" az="-27.449" break_y="23.7" break_angle="1.4" break_length="7.1" pitch_type="FC" type_confidence=".839" zone="13" nasty="37" spin_dir="174.309" spin_rate="534.054"  cc="" mt=""/></atbat><atbat num="96" b="1" s="2" o="3" start_tfs="233027" start_tfs_zulu="2012-05-17T03:30:27Z" batter="543333" stand="L" b_height="6-4" pitcher="445968" p_throws="L" des="Eric Hosmer grounds out, second baseman Robert Andino to first baseman Wilson Betemit.  " event="Groundout"><pitch des="Ball" id="725" type="B" tfs="233038" tfs_zulu="2012-05-17T03:30:38Z" x="117.60" y="112.25" sv_id="120516_223039" start_speed="87.9" end_speed="79.5" sz_top="3.68" sz_bot="1.77" pfx_x="0.26" pfx_z="5.62" px="-0.406" pz="3.961" x0="1.795" y0="50.0" z0="5.921" vx0="-5.631" vy0="-128.785" vz0="-0.399" ax="0.424" ay="32.111" az="-22.868" break_y="23.7" break_angle="2.3" break_length="5.7" pitch_type="FC" type_confidence=".923" zone="11" nasty="64" spin_dir="177.393" spin_rate="1049.422"  cc="" mt=""/><pitch des="Called Strike" id="726" type="S" tfs="233057" tfs_zulu="2012-05-17T03:30:57Z" x="98.71" y="133.84" sv_id="120516_223058" start_speed="81.4" end_speed="73.1" sz_top="3.59" sz_bot="1.73" pfx_x="-10.37" pfx_z="-2.15" px="0.106" pz="3.034" x0="2.115" y0="50.0" z0="5.927" vx0="-1.556" vy0="-119.439" vz0="0.85" ax="-14.411" ay="31.188" az="-35.088" break_y="23.6" break_angle="22.9" break_length="11.2" pitch_type="SL" type_confidence=".964" zone="2" nasty="25" spin_dir="281.432" spin_rate="1785.879"  cc="" mt=""/><pitch des="Foul" id="727" type="S" tfs="233114" tfs_zulu="2012-05-17T03:31:14Z" x="158.80" y="155.42" sv_id="120516_223114" start_speed="89.0" end_speed="79.9" sz_top="3.59" sz_bot="1.69" pfx_x="0.54" pfx_z="6.5" px="-1.736" pz="2.105" x0="1.624" y0="50.0" z0="5.718" vx0="-8.691" vy0="-130.133" vz0="-4.945" ax="0.899" ay="35.667" az="-21.323" break_y="23.6" break_angle="3.5" break_length="5.6" pitch_type="FC" type_confidence=".906" zone="13" nasty="32" spin_dir="175.266" spin_rate="1213.864"  cc="" mt=""/><pitch des="Foul" id="728" type="S" tfs="233138" tfs_zulu="2012-05-17T03:31:38Z" x="129.61" y="129.52" sv_id="120516_223138" start_speed="88.3" end_speed="81.3" sz_top="3.59" sz_bot="1.69" pfx_x="-1.9" pfx_z="4.85" px="-0.797" pz="3.231" x0="1.514" y0="50.0" z0="5.882" vx0="-5.265" vy0="-129.439" vz0="-2.079" ax="-3.211" ay="28.051" az="-23.897" break_y="23.8" break_angle="10.0" break_length="5.9" pitch_type="FC" type_confidence=".923" zone="11" nasty="52" spin_dir="201.202" spin_rate="995.069"  cc="" mt=""/><pitch des="In play, out(s)" id="729" type="X" tfs="233219" tfs_zulu="2012-05-17T03:32:19Z" x="131.33" y="154.56" sv_id="120516_223202" start_speed="89.9" end_speed="82.1" sz_top="3.59" sz_bot="1.69" pfx_x="-0.12" pfx_z="5.12" px="-0.955" pz="2.117" x0="1.548" y0="50.0" z0="5.75" vx0="-6.427" vy0="-131.608" vz0="-4.883" ax="-0.199" ay="31.596" az="-23.254" break_y="23.7" break_angle="3.9" break_length="5.8" pitch_type="FC" type_confidence=".909" zone="13" nasty="53" spin_dir="181.276" spin_rate="983.542"  cc="" mt=""/></atbat></bottom></inning>