<!--Copyright 2012 MLB Advanced Media, L.P.  Use of any content on this page acknowledges agreement to the terms posted here http://gdx.mlb.com/components/copyright.txt--><inning num="6" away_team="ana" home_team="sea" next="Y"><top><atbat num="37" b="1" s="0" o="0" start_tfs="232537" start_tfs_zulu="2012-05-25T03:25:37Z" batter="405395" stand="R" b_height="6-3" pitcher="450306" p_throws="L" des="Albert Pujols singles on a line drive to left fielder Alex Liddi.  " event="Single"><pitch des="Ball" id="281" type="B" tfs="232558" tfs_zulu="2012-05-25T03:25:58Z" x="132.19" y="192.55" sv_id="120524_202600" start_speed="80.4" end_speed="74.2" sz_top="3.47" sz_bot="1.65" pfx_x="10.57" pfx_z="0.94" px="-1.001" pz="0.492" x0="1.722" y0="50.0" z0="5.418" vx0="-9.475" vy0="-117.503" vz0="-4.741" ax="14.69" ay="23.603" az="-30.797" break_y="23.8" break_angle="-22.3" break_length="10.0" pitch_type="CH" type_confidence=".904" zone="13" nasty="68" spin_dir="95.355" spin_rate="1821.691"  cc="" mt=""/><pitch des="In play, no out" id="282" type="X" tfs="232613" tfs_zulu="2012-05-25T03:26:13Z" x="83.26" y="151.10" sv_id="120524_202615" start_speed="87.1" end_speed="79.1" sz_top="3.25" sz_bot="1.55" pfx_x="8.89" pfx_z="6.17" px="0.461" pz="2.208" x0="1.914" y0="50.0" z0="5.394" vx0="-6.513" vy0="-127.498" vz0="-3.544" ax="14.394" ay="30.24" az="-22.109" break_y="23.7" break_angle="-29.4" break_length="6.6" pitch_type="FT" type_confidence=".916" zone="6" nasty="47" spin_dir="124.964" spin_rate="1998.575"  cc="That was pitch number 75 for Jason Vargas; his effectiveness may start slipping, as he holds opposing hitters to a .184 average in the first 75 pitches but they hit .229 off him after that." mt=""/><runner id="405395" start="" end="1B" event="Single"/></atbat><action b="1" s="2" o="0" des="With Mark Trumbo batting, Albert Pujols steals (2) 2nd base.  " event="Stolen Base 2B" tfs="232808" tfs_zulu="2012-05-25T03:28:08Z" player="405395" pitch="3"/><atbat num="38" b="1" s="3" o="1" start_tfs="232644" start_tfs_zulu="2012-05-25T03:26:44Z" batter="444432" stand="R" b_height="6-4" pitcher="450306" p_throws="L" des="Mark Trumbo strikes out swinging.  " event="Strikeout"><pitch des="Ball" id="286" type="B" tfs="232655" tfs_zulu="2012-05-25T03:26:55Z" x="131.33" y="138.15" on_1b="405395" sv_id="120524_202657" start_speed="88.0" end_speed="79.8" sz_top="3.68" sz_bot="1.74" pfx_x="6.89" pfx_z="5.45" px="-1.046" pz="2.881" x0="1.566" y0="50.0" z0="5.46" vx0="-8.84" vy0="-128.712" vz0="-1.926" ax="11.364" ay="30.994" az="-23.116" break_y="23.7" break_angle="-21.5" break_length="6.3" pitch_type="FF" type_confidence=".895" zone="11" nasty="67" spin_dir="128.558" spin_rate="1638.014"  cc="" mt=""/><pitch des="Called Strike" id="287" type="S" tfs="232717" tfs_zulu="2012-05-25T03:27:17Z" x="127.04" y="132.11" on_1b="405395" sv_id="120524_202719" start_speed="88.0" end_speed="79.6" sz_top="3.64" sz_bot="1.82" pfx_x="8.0" pfx_z="7.3" px="-0.849" pz="2.976" x0="1.642" y0="50.0" z0="5.531" vx0="-8.892" vy0="-128.702" vz0="-2.457" ax="13.166" ay="31.343" az="-20.085" break_y="23.7" break_angle="-28.1" break_length="5.8" pitch_type="FF" type_confidence=".635" zone="11" nasty="53" spin_dir="132.559" spin_rate="2014.855"  cc="" mt=""/><pitch des="Swinging Strike" id="288" type="S" tfs="232741" tfs_zulu="2012-05-25T03:27:41Z" x="108.15" y="181.33" on_1b="405395" sv_id="120524_202744" start_speed="81.4" end_speed="74.8" sz_top="3.5" sz_bot="1.63" pfx_x="12.09" pfx_z="0.87" px="-0.252" pz="0.938" x0="1.674" y0="50.0" z0="5.453" vx0="-8.176" vy0="-119.098" vz0="-3.974" ax="17.171" ay="25.235" az="-30.864" break_y="23.8" break_angle="-26.2" break_length="10.1" pitch_type="CH" type_confidence=".906" zone="13" nasty="25" spin_dir="94.363" spin_rate="2097.749"  cc="" mt=""/><runner id="405395" start="1B" end="2B" event="Stolen Base 2B"/><pitch des="Swinging Strike" id="292" type="S" tfs="232815" tfs_zulu="2012-05-25T03:28:15Z" x="136.48" y="120.02" on_2b="405395" sv_id="120524_202817" start_speed="87.9" end_speed="80.0" sz_top="3.5" sz_bot="1.63" pfx_x="7.92" pfx_z="8.53" px="-1.159" pz="3.645" x0="1.647" y0="50.0" z0="5.479" vx0="-9.686" vy0="-128.544" vz0="-1.079" ax="13.114" ay="29.184" az="-17.966" break_y="23.7" break_angle="-31.0" break_length="5.2" pitch_type="FF" type_confidence=".650" zone="11" nasty="69" spin_dir="137.294" spin_rate="2182.206"  cc="" mt=""/></atbat><atbat num="39" b="3" s="2" o="1" start_tfs="232849" start_tfs_zulu="2012-05-25T03:28:49Z" batter="434778" stand="R" b_height="6-1" pitcher="450306" p_throws="L" des="Kendrys Morales singles on a line drive to left fielder Alex Liddi.    Albert Pujols scores.  " event="Single" score="T" home_team_runs="0" away_team_runs="3"><pitch des="Called Strike" id="296" type="S" tfs="232846" tfs_zulu="2012-05-25T03:28:46Z" x="90.13" y="158.01" on_2b="405395" sv_id="120524_202848" start_speed="80.4" end_speed="73.4" sz_top="3.39" sz_bot="1.53" pfx_x="11.16" pfx_z="1.12" px="0.246" pz="1.824" x0="1.694" y0="50.0" z0="5.476" vx0="-6.677" vy0="-117.654" vz0="-1.805" ax="15.393" ay="25.675" az="-30.551" break_y="23.7" break_angle="-24.4" break_length="10.0" pitch_type="CH" type_confidence=".905" zone="9" nasty="58" spin_dir="96.019" spin_rate="1908.620"  cc="" mt=""/><pitch des="Ball In Dirt" id="297" type="B" tfs="232909" tfs_zulu="2012-05-25T03:29:09Z" x="105.58" y="181.33" on_2b="405395" sv_id="120524_202911" start_speed="79.8" end_speed="73.6" sz_top="3.6" sz_bot="1.7" pfx_x="13.27" pfx_z="1.35" px="-0.109" pz="0.884" x0="1.661" y0="50.0" z0="5.486" vx0="-8.024" vy0="-116.765" vz0="-3.993" ax="18.179" ay="23.503" az="-30.247" break_y="23.8" break_angle="-28.3" break_length="10.4" pitch_type="CH" type_confidence=".905" zone="13" nasty="20" spin_dir="96.051" spin_rate="2271.359"  cc="" mt=""/><pitch des="Ball" id="298" type="B" tfs="232933" tfs_zulu="2012-05-25T03:29:33Z" x="135.62" y="115.70" on_2b="405395" sv_id="120524_202935" start_speed="88.1" end_speed="79.4" sz_top="3.6" sz_bot="1.66" pfx_x="5.33" pfx_z="8.87" px="-1.022" pz="3.911" x0="1.574" y0="50.0" z0="5.561" vx0="-8.283" vy0="-129.004" vz0="-0.69" ax="8.764" ay="32.711" az="-17.51" break_y="23.7" break_angle="-20.7" break_length="4.7" pitch_type="FF" type_confidence=".888" zone="11" nasty="69" spin_dir="149.136" spin_rate="1921.197"  cc="" mt=""/><pitch des="Called Strike" id="299" type="S" tfs="233038" tfs_zulu="2012-05-25T03:30:38Z" x="72.10" y="164.92" on_2b="405395" sv_id="120524_203040" start_speed="88.2" end_speed="80.8" sz_top="3.6" sz_bot="1.7" pfx_x="9.27" pfx_z="6.46" px="0.875" pz="1.872" x0="1.847" y0="50.0" z0="5.425" vx0="-5.527" vy0="-129.111" vz0="-4.844" ax="15.533" ay="28.685" az="-21.28" break_y="23.8" break_angle="-32.7" break_length="6.4" pitch_type="FT" type_confidence=".916" zone="14" nasty="69" spin_dir="125.044" spin_rate="2131.877"  cc="" mt=""/><pitch des="Ball" id="300" type="B" tfs="233116" tfs_zulu="2012-05-25T03:31:16Z" x="149.36" y="144.20" on_2b="405395" sv_id="120524_203118" start_speed="88.3" end_speed="80.6" sz_top="3.51" sz_bot="1.67" pfx_x="9.6" pfx_z="7.54" px="-1.606" pz="2.526" x0="1.565" y0="50.0" z0="5.5" vx0="-11.204" vy0="-128.912" vz0="-3.7" ax="16.036" ay="28.763" az="-19.507" break_y="23.7" break_angle="-33.8" break_length="6.0" pitch_type="FT" type_confidence=".900" zone="13" nasty="28" spin_dir="128.306" spin_rate="2299.812"  cc="Jason Vargas has thrown 83 pitches but has plenty left in the tank, with his fastball sitting at 88 over the past 10 pitches." mt=""/><pitch des="In play, run(s)" id="301" type="X" tfs="233140" tfs_zulu="2012-05-25T03:31:40Z" x="136.48" y="119.16" on_2b="405395" sv_id="120524_203142" start_speed="88.0" end_speed="79.5" sz_top="3.51" sz_bot="1.67" pfx_x="7.04" pfx_z="6.88" px="-1.116" pz="3.603" x0="1.494" y0="50.0" z0="5.524" vx0="-8.874" vy0="-128.706" vz0="-0.722" ax="11.574" ay="31.553" az="-20.776" break_y="23.7" break_angle="-24.2" break_length="5.7" pitch_type="FF" type_confidence=".900" zone="11" nasty="68" spin_dir="134.562" spin_rate="1831.049"  cc="" mt=""/><runner id="405395" start="2B" end="" event="Single" score="T" rbi="T" earned="T"/><runner id="434778" start="" end="1B" event="Single"/></atbat><atbat num="40" b="2" s="3" o="2" start_tfs="233223" start_tfs_zulu="2012-05-25T03:32:23Z" batter="435062" stand="R" b_height="5-10" pitcher="450306" p_throws="L" des="Howard Kendrick strikes out swinging.  " event="Strikeout"><pitch des="Ball" id="307" type="B" tfs="233228" tfs_zulu="2012-05-25T03:32:28Z" x="55.79" y="162.33" on_1b="434778" sv_id="120524_203230" start_speed="88.3" end_speed="79.4" sz_top="3.63" sz_bot="1.6" pfx_x="8.2" pfx_z="7.3" px="1.264" pz="1.746" x0="1.842" y0="50.0" z0="5.407" vx0="-4.129" vy0="-129.27" vz0="-5.241" ax="13.472" ay="34.263" az="-20.105" break_y="23.6" break_angle="-30.0" break_length="6.2" pitch_type="FF" type_confidence=".791" zone="14" nasty="77" spin_dir="131.857" spin_rate="2029.933"  cc="" mt=""/><pitch des="Ball" id="308" type="B" tfs="233249" tfs_zulu="2012-05-25T03:32:49Z" x="54.08" y="139.02" on_1b="434778" sv_id="120524_203251" start_speed="88.0" end_speed="79.3" sz_top="3.64" sz_bot="1.52" pfx_x="9.09" pfx_z="7.39" px="1.357" pz="2.719" x0="1.86" y0="50.0" z0="5.532" vx0="-4.226" vy0="-128.891" vz0="-3.119" ax="14.907" ay="32.991" az="-19.969" break_y="23.7" break_angle="-33.7" break_length="6.2" pitch_type="FT" type_confidence=".917" zone="12" nasty="27" spin_dir="129.309" spin_rate="2168.564"  cc="" mt=""/><pitch des="Called Strike" id="309" type="S" tfs="233312" tfs_zulu="2012-05-25T03:33:12Z" x="102.15" y="160.60" on_1b="434778" sv_id="120524_203314" start_speed="88.3" end_speed="79.8" sz_top="3.59" sz_bot="1.57" pfx_x="8.86" pfx_z="6.73" px="-0.075" pz="1.906" x0="1.689" y0="50.0" z0="5.357" vx0="-7.355" vy0="-129.235" vz0="-4.575" ax="14.646" ay="32.536" az="-20.968" break_y="23.7" break_angle="-30.2" break_length="6.3" pitch_type="FT" type_confidence=".925" zone="8" nasty="41" spin_dir="127.421" spin_rate="2070.201"  cc="" mt=""/><pitch des="Called Strike" id="310" type="S" tfs="233335" tfs_zulu="2012-05-25T03:33:35Z" x="121.03" y="159.74" on_1b="434778" sv_id="120524_203337" start_speed="87.8" end_speed="79.7" sz_top="3.47" sz_bot="1.59" pfx_x="8.32" pfx_z="8.1" px="-0.603" pz="1.893" x0="1.547" y0="50.0" z0="5.369" vx0="-8.126" vy0="-128.381" vz0="-5.018" ax="13.667" ay="30.586" az="-18.796" break_y="23.7" break_angle="-30.6" break_length="5.8" pitch_type="FT" type_confidence=".882" zone="7" nasty="59" spin_dir="134.389" spin_rate="2161.216"  cc="" mt=""/><pitch des="Swinging Strike" id="311" type="S" tfs="233404" tfs_zulu="2012-05-25T03:34:04Z" x="117.60" y="126.93" on_1b="434778" sv_id="120524_203406" start_speed="87.5" end_speed="79.8" sz_top="3.34" sz_bot="1.48" pfx_x="8.68" pfx_z="5.55" px="-0.551" pz="3.435" x0="1.576" y0="50.0" z0="5.499" vx0="-8.187" vy0="-128.038" vz0="-0.633" ax="14.271" ay="28.868" az="-22.977" break_y="23.7" break_angle="-28.3" break_length="6.5" pitch_type="FT" type_confidence=".915" zone="11" nasty="64" spin_dir="122.801" spin_rate="1923.735"  cc="" mt=""/></atbat><atbat num="41" b="1" s="1" o="3" start_tfs="233432" start_tfs_zulu="2012-05-25T03:34:32Z" batter="430947" stand="R" b_height="5-10" pitcher="450306" p_throws="L" des="Erick Aybar bunt grounds out to catcher Miguel Olivo.  Erick Aybar out on batter interference.  " event="Batter Interference"><pitch des="Called Strike" id="315" type="S" tfs="233438" tfs_zulu="2012-05-25T03:34:38Z" x="81.55" y="143.33" on_1b="434778" sv_id="120524_203440" start_speed="88.0" end_speed="79.7" sz_top="3.23" sz_bot="1.69" pfx_x="8.29" pfx_z="7.14" px="0.565" pz="2.698" x0="1.931" y0="50.0" z0="5.404" vx0="-6.157" vy0="-128.908" vz0="-2.81" ax="13.688" ay="31.501" az="-20.316" break_y="23.7" break_angle="-30.2" break_length="6.0" pitch_type="FT" type_confidence=".793" zone="6" nasty="52" spin_dir="130.903" spin_rate="2038.176"  cc="" mt=""/><pitch des="Ball In Dirt" id="316" type="B" tfs="233457" tfs_zulu="2012-05-25T03:34:57Z" x="89.27" y="205.50" on_1b="434778" sv_id="120524_203459" start_speed="78.8" end_speed="72.4" sz_top="3.23" sz_bot="1.65" pfx_x="10.25" pfx_z="0.8" px="0.264" pz="-0.103" x0="1.729" y0="50.0" z0="5.325" vx0="-6.314" vy0="-115.274" vz0="-5.407" ax="13.575" ay="24.569" az="-31.037" break_y="23.8" break_angle="-21.1" break_length="10.6" pitch_type="CH" type_confidence=".900" zone="14" nasty="25" spin_dir="94.788" spin_rate="1714.465"  cc="" mt=""/><pitch des="In play, out(s)" id="317" type="X" tfs="233521" tfs_zulu="2012-05-25T03:35:21Z" x="78.11" y="171.83" on_1b="434778" sv_id="120524_203524" start_speed="79.7" end_speed="72.7" sz_top="3.14" sz_bot="1.49" pfx_x="10.89" pfx_z="1.83" px="0.65" pz="1.329" x0="1.734" y0="50.0" z0="5.518" vx0="-5.702" vy0="-116.669" vz0="-3.099" ax="14.736" ay="25.629" az="-29.62" break_y="23.7" break_angle="-24.2" break_length="10.0" pitch_type="CH" type_confidence=".904" zone="14" nasty="58" spin_dir="99.833" spin_rate="1859.744"  cc="" mt=""/><runner id="434778" start="1B" end="" event="Batter Interference"/></atbat></top><bottom><atbat num="42" b="0" s="0" o="0" start_tfs="233730" start_tfs_zulu="2012-05-25T03:37:30Z" batter="459431" stand="L" b_height="6-4" pitcher="429717" p_throws="R" des="Michael Saunders singles on a ground ball to shortstop Erick Aybar.  " event="Single"><pitch des="In play, no out" id="324" type="X" tfs="233739" tfs_zulu="2012-05-25T03:37:39Z" x="141.63" y="155.42" sv_id="120524_203741" start_speed="87.6" end_speed="79.8" sz_top="3.7" sz_bot="1.66" pfx_x="-7.37" pfx_z="5.9" px="-1.244" pz="2.074" x0="-0.514" y0="50.0" z0="6.16" vx0="0.565" vy0="-128.34" vz0="-5.82" ax="-12.086" ay="30.857" az="-22.425" break_y="23.7" break_angle="26.7" break_length="6.6" pitch_type="FS" type_confidence=".569" zone="13" nasty="99" spin_dir="231.108" spin_rate="1755.302"  cc="" mt=""/><runner id="459431" start="" end="1B" event="Single"/></atbat><atbat num="43" b="2" s="3" o="1" start_tfs="233823" start_tfs_zulu="2012-05-25T03:38:23Z" batter="453895" stand="R" b_height="6-2" pitcher="429717" p_throws="R" des="Brendan Ryan called out on strikes.  " event="Strikeout"><pitch des="Missed Bunt" id="328" type="S" tfs="233833" tfs_zulu="2012-05-25T03:38:33Z" x="83.26" y="139.88" on_1b="459431" sv_id="120524_203835" start_speed="83.7" end_speed="77.6" sz_top="3.62" sz_bot="1.67" pfx_x="1.89" pfx_z="1.55" px="0.607" pz="2.682" x0="-0.909" y0="50.0" z0="6.144" vx0="3.079" vy0="-122.744" vz0="-2.256" ax="2.878" ay="24.225" az="-29.737" break_y="23.8" break_angle="-6.5" break_length="8.1" pitch_type="FC" type_confidence=".815" zone="6" nasty="53" spin_dir="130.258" spin_rate="445.738"  cc="" mt=""/><pitch des="Ball" id="329" type="B" tfs="233858" tfs_zulu="2012-05-25T03:38:58Z" x="67.81" y="179.60" on_1b="459431" sv_id="120524_203900" start_speed="83.8" end_speed="78.1" sz_top="3.62" sz_bot="1.67" pfx_x="3.08" pfx_z="-0.17" px="1.096" pz="1.054" x0="-0.692" y0="50.0" z0="6.156" vx0="3.365" vy0="-122.74" vz0="-5.693" ax="4.696" ay="24.093" az="-32.359" break_y="23.9" break_angle="-8.9" break_length="9.0" pitch_type="FC" type_confidence=".749" zone="14" nasty="44" spin_dir="87.744" spin_rate="555.496"  cc="" mt=""/><pitch des="Called Strike" id="330" type="S" tfs="233917" tfs_zulu="2012-05-25T03:39:17Z" x="98.71" y="125.20" on_1b="459431" sv_id="120524_203919" start_speed="84.4" end_speed="78.1" sz_top="3.72" sz_bot="1.69" pfx_x="2.47" pfx_z="1.38" px="0.128" pz="3.24" x0="-0.869" y0="50.0" z0="6.238" vx0="1.655" vy0="-123.811" vz0="-1.195" ax="3.829" ay="24.836" az="-29.962" break_y="23.8" break_angle="-7.8" break_length="8.0" pitch_type="FC" type_confidence=".872" zone="2" nasty="29" spin_dir="120.016" spin_rate="518.159"  cc="" mt=""/><pitch des="Ball" id="331" type="B" tfs="233940" tfs_zulu="2012-05-25T03:39:40Z" x="69.53" y="175.28" on_1b="459431" sv_id="120524_203942" start_speed="84.4" end_speed="78.2" sz_top="3.76" sz_bot="1.82" pfx_x="1.62" pfx_z="0.29" px="0.992" pz="1.315" x0="-0.674" y0="50.0" z0="6.165" vx0="3.545" vy0="-123.668" vz0="-5.324" ax="2.499" ay="25.733" az="-31.651" break_y="23.8" break_angle="-5.5" break_length="8.6" pitch_type="FC" type_confidence=".791" zone="14" nasty="45" spin_dir="101.821" spin_rate="299.516"  cc="" mt=""/><pitch des="Called Strike" id="332" type="S" tfs="234001" tfs_zulu="2012-05-25T03:40:01Z" x="103.86" y="163.19" on_1b="459431" sv_id="120524_204003" start_speed="89.5" end_speed="82.6" sz_top="3.76" sz_bot="1.78" pfx_x="-8.94" pfx_z="5.39" px="0.072" pz="1.743" x0="-0.426" y0="50.0" z0="6.157" vx0="4.289" vy0="-131.053" vz0="-7.01" ax="-15.519" ay="28.233" az="-22.753" break_y="23.8" break_angle="31.2" break_length="6.6" pitch_type="FT" type_confidence=".810" zone="14" nasty="47" spin_dir="238.739" spin_rate="2009.765"  cc="" mt=""/></atbat><action b="2" s="0" o="1" des="With Dustin Ackley batting, Michael Saunders steals (6) 2nd base.  " event="Stolen Base 2B" tfs="234108" tfs_zulu="2012-05-25T03:41:08Z" player="459431" pitch="2"/><atbat num="44" b="2" s="0" o="2" start_tfs="234030" start_tfs_zulu="2012-05-25T03:40:30Z" batter="554429" stand="L" b_height="6-1" pitcher="429717" p_throws="R" des="Dustin Ackley flies out to center fielder Peter Bourjos.  " event="Flyout"><pitch des="Ball" id="336" type="B" tfs="234034" tfs_zulu="2012-05-25T03:40:34Z" x="145.06" y="151.10" on_1b="459431" sv_id="120524_204036" start_speed="88.1" end_speed="80.8" sz_top="3.56" sz_bot="1.55" pfx_x="-3.69" pfx_z="5.91" px="-1.391" pz="2.27" x0="-0.584" y0="50.0" z0="6.248" vx0="-0.833" vy0="-129.055" vz0="-5.718" ax="-6.169" ay="29.169" az="-22.222" break_y="23.8" break_angle="15.1" break_length="5.9" pitch_type="FF" type_confidence=".697" zone="13" nasty="40" spin_dir="211.793" spin_rate="1316.268"  cc="" mt=""/><pitch des="Ball" id="337" type="B" tfs="234053" tfs_zulu="2012-05-25T03:40:53Z" x="127.04" y="107.07" on_1b="459431" sv_id="120524_204055" start_speed="87.3" end_speed="80.0" sz_top="3.65" sz_bot="1.62" pfx_x="-5.8" pfx_z="6.05" px="-0.736" pz="4.059" x0="-0.58" y0="50.0" z0="6.336" vx0="1.505" vy0="-128.042" vz0="-1.346" ax="-9.561" ay="28.3" az="-22.135" break_y="23.8" break_angle="22.4" break_length="6.0" pitch_type="FS" type_confidence=".534" zone="11" nasty="55" spin_dir="223.602" spin_rate="1570.797"  cc="" mt=""/><runner id="459431" start="1B" end="2B" event="Stolen Base 2B"/><pitch des="In play, out(s)" id="341" type="X" tfs="234126" tfs_zulu="2012-05-25T03:41:26Z" x="101.29" y="138.15" on_2b="459431" sv_id="120524_204128" start_speed="88.8" end_speed="81.4" sz_top="3.53" sz_bot="1.63" pfx_x="-4.9" pfx_z="4.92" px="-0.052" pz="2.787" x0="-0.486" y0="50.0" z0="6.135" vx0="2.739" vy0="-130.169" vz0="-3.946" ax="-8.336" ay="29.32" az="-23.729" break_y="23.8" break_angle="17.5" break_length="6.2" pitch_type="FF" type_confidence=".757" zone="5" nasty="23" spin_dir="224.627" spin_rate="1322.533"  cc="" mt=""/></atbat><atbat num="45" b="1" s="3" o="3" start_tfs="234205" start_tfs_zulu="2012-05-25T03:42:05Z" batter="499926" stand="R" b_height="6-4" pitcher="429717" p_throws="R" des="Alex Liddi strikes out swinging.  " event="Strikeout"><pitch des="Called Strike" id="345" type="S" tfs="234207" tfs_zulu="2012-05-25T03:42:07Z" x="55.79" y="156.29" on_2b="459431" sv_id="120524_204209" start_speed="85.7" end_speed="79.5" sz_top="3.84" sz_bot="1.9" pfx_x="2.05" pfx_z="1.24" px="1.346" pz="2.019" x0="-0.759" y0="50.0" z0="6.076" vx0="4.558" vy0="-125.587" vz0="-3.982" ax="3.275" ay="25.571" az="-30.116" break_y="23.8" break_angle="-7.6" break_length="7.9" pitch_type="FC" type_confidence=".898" zone="14" nasty="47" spin_dir="122.146" spin_rate="446.825"  cc="" mt=""/><pitch des="Ball" id="346" type="B" tfs="234225" tfs_zulu="2012-05-25T03:42:25Z" x="68.67" y="177.01" on_2b="459431" sv_id="120524_204227" start_speed="85.2" end_speed="78.8" sz_top="3.84" sz_bot="1.9" pfx_x="1.61" pfx_z="-0.2" px="1.029" pz="1.031" x0="-0.656" y0="50.0" z0="5.959" vx0="3.628" vy0="-124.752" vz0="-5.515" ax="2.518" ay="26.389" az="-32.411" break_y="23.8" break_angle="-5.4" break_length="8.7" pitch_type="FC" type_confidence=".843" zone="14" nasty="44" spin_dir="84.623" spin_rate="294.121"  cc="" mt=""/><pitch des="Swinging Strike" id="347" type="S" tfs="234244" tfs_zulu="2012-05-25T03:42:44Z" x="69.53" y="165.78" on_2b="459431" sv_id="120524_204246" start_speed="84.9" end_speed="78.7" sz_top="3.71" sz_bot="1.74" pfx_x="3.15" pfx_z="1.16" px="0.962" pz="1.523" x0="-0.818" y0="50.0" z0="6.009" vx0="3.364" vy0="-124.436" vz0="-4.845" ax="4.932" ay="25.454" az="-30.278" break_y="23.8" break_angle="-10.0" break_length="8.2" pitch_type="FC" type_confidence=".889" zone="14" nasty="65" spin_dir="111.029" spin_rate="616.041"  cc="" mt=""/><pitch des="Swinging Strike" id="348" type="S" tfs="234305" tfs_zulu="2012-05-25T03:43:05Z" x="55.79" y="170.10" on_2b="459431" sv_id="120524_204307" start_speed="85.1" end_speed="79.3" sz_top="3.71" sz_bot="1.74" pfx_x="2.12" pfx_z="0.1" px="1.352" pz="1.477" x0="-0.688" y0="50.0" z0="6.111" vx0="4.348" vy0="-124.642" vz0="-4.935" ax="3.35" ay="24.304" az="-31.948" break_y="23.9" break_angle="-7.1" break_length="8.5" pitch_type="FC" type_confidence=".867" zone="14" nasty="35" spin_dir="93.860" spin_rate="390.813"  cc="" mt=""/><runner id="459431" start="2B" end="" event="Strikeout"/></atbat></bottom></inning>