<!--Copyright 2012 MLB Advanced Media, L.P.  Use of any content on this page acknowledges agreement to the terms posted here http://gdx.mlb.com/components/copyright.txt--><inning num="8" away_team="chn" home_team="pit" next="Y"><top><action b="0" s="0" o="0" des="Defensive switch from left field to right field for Jose Tabata.  " event="Defensive Switch" tfs="213827" tfs_zulu="2012-05-26T01:38:27Z" player="467798" pitch="3"/><action b="0" s="0" o="0" des="Pitcher Change: Juan Cruz replaces Jason Grilli, batting 6th.  " event="Pitching Substitution" tfs="213827" tfs_zulu="2012-05-26T01:38:27Z" player="407297" pitch="3"/><action b="0" s="0" o="0" des="Defensive Substitution:  Gorkys Hernandez replaces right fielder Josh Harrison, batting 2nd, playing left field.  " event="Defensive Sub" tfs="213827" tfs_zulu="2012-05-26T01:38:27Z" player="491676" pitch="3"/><atbat num="60" b="2" s="2" o="0" start_tfs="213917" start_tfs_zulu="2012-05-26T01:39:17Z" batter="458628" stand="R" b_height="6-4" pitcher="407297" p_throws="R" des="Joe Mather singles on a ground ball to right fielder Jose Tabata.  " event="Single"><pitch des="Ball" id="489" type="B" tfs="213940" tfs_zulu="2012-05-26T01:39:40Z" x="103.00" y="113.11" sv_id="120525_213942" start_speed="87.5" end_speed="81.6" sz_top="3.39" sz_bot="1.54" pfx_x="-1.42" pfx_z="6.05" px="-0.113" pz="3.873" x0="-2.626" y0="50.0" z0="5.747" vx0="6.865" vy0="-128.12" vz0="-0.469" ax="-2.393" ay="22.741" az="-21.888" break_y="23.9" break_angle="3.2" break_length="5.3" pitch_type="FC" type_confidence=".801" zone="11" nasty="36" spin_dir="193.095" spin_rate="1195.853"  cc="" mt=""/><pitch des="Foul" id="490" type="S" tfs="214001" tfs_zulu="2012-05-26T01:40:01Z" x="100.43" y="137.29" sv_id="120525_214003" start_speed="87.8" end_speed="81.5" sz_top="3.39" sz_bot="1.54" pfx_x="-3.1" pfx_z="6.13" px="0.024" pz="2.817" x0="-2.567" y0="50.0" z0="5.581" vx0="7.624" vy0="-128.455" vz0="-2.763" ax="-5.236" ay="24.302" az="-21.769" break_y="23.8" break_angle="9.8" break_length="5.4" pitch_type="CH" type_confidence=".467" zone="2" nasty="22" spin_dir="206.711" spin_rate="1315.554"  cc="" mt=""/><pitch des="Ball" id="491" type="B" tfs="214031" tfs_zulu="2012-05-26T01:40:31Z" x="59.23" y="173.55" sv_id="120525_214032" start_speed="94.1" end_speed="86.3" sz_top="3.39" sz_bot="1.54" pfx_x="-6.51" pfx_z="10.1" px="1.281" pz="1.291" x0="-1.971" y0="50.0" z0="5.702" vx0="11.083" vy0="-137.275" vz0="-9.551" ax="-12.371" ay="31.537" az="-12.898" break_y="23.8" break_angle="33.4" break_length="3.9" pitch_type="FF" type_confidence=".919" zone="14" nasty="68" spin_dir="212.690" spin_rate="2420.624"  cc="" mt=""/><pitch des="Foul" id="492" type="S" tfs="214107" tfs_zulu="2012-05-26T01:41:07Z" x="96.14" y="154.56" sv_id="120525_214108" start_speed="80.5" end_speed="73.7" sz_top="3.39" sz_bot="1.54" pfx_x="8.6" pfx_z="4.25" px="0.164" pz="2.218" x0="-2.614" y0="50.0" z0="5.533" vx0="3.846" vy0="-117.93" vz0="-2.001" ax="11.924" ay="25.702" az="-26.204" break_y="23.8" break_angle="-25.4" break_length="8.7" pitch_type="SL" type_confidence=".878" zone="5" nasty="23" spin_dir="116.596" spin_rate="1640.482"  cc="" mt=""/><pitch des="In play, no out" id="493" type="X" tfs="214149" tfs_zulu="2012-05-26T01:41:49Z" x="64.38" y="129.52" sv_id="120525_214137" start_speed="94.2" end_speed="87.0" sz_top="3.39" sz_bot="1.54" pfx_x="-6.34" pfx_z="10.22" px="1.034" pz="2.962" x0="-1.913" y0="50.0" z0="5.818" vx0="10.276" vy0="-137.685" vz0="-5.511" ax="-12.245" ay="28.877" az="-12.369" break_y="23.8" break_angle="36.9" break_length="3.5" pitch_type="FF" type_confidence=".912" zone="12" nasty="55" spin_dir="211.726" spin_rate="2453.503"  cc="" mt=""/><runner id="458628" start="" end="1B" event="Single"/></atbat><atbat num="61" b="1" s="3" o="1" start_tfs="214153" start_tfs_zulu="2012-05-26T01:41:53Z" batter="445933" stand="L" b_height="6-5" pitcher="407297" p_throws="R" des="Bryan LaHair strikes out swinging.  " event="Strikeout"><pitch des="Ball" id="497" type="B" tfs="214223" tfs_zulu="2012-05-26T01:42:23Z" x="138.20" y="120.88" on_1b="458628" sv_id="120525_214224" start_speed="78.8" end_speed="72.7" sz_top="3.66" sz_bot="1.73" pfx_x="9.11" pfx_z="0.72" px="-1.145" pz="3.542" x0="-2.769" y0="50.0" z0="5.795" vx0="1.004" vy0="-115.597" vz0="1.702" ax="12.274" ay="22.468" az="-31.134" break_y="23.8" break_angle="-22.0" break_length="10.0" pitch_type="SL" type_confidence=".901" zone="11" nasty="88" spin_dir="94.843" spin_rate="1545.949"  cc="" mt=""/><pitch des="Foul" id="498" type="S" tfs="214246" tfs_zulu="2012-05-26T01:42:46Z" x="111.59" y="139.88" on_1b="458628" sv_id="120525_214248" start_speed="89.0" end_speed="82.5" sz_top="3.66" sz_bot="1.73" pfx_x="-0.61" pfx_z="6.94" px="-0.327" pz="2.62" x0="-2.605" y0="50.0" z0="5.621" vx0="6.083" vy0="-130.355" vz0="-3.847" ax="-1.059" ay="25.944" az="-20.095" break_y="23.8" break_angle="-.3" break_length="4.9" pitch_type="FC" type_confidence=".481" zone="4" nasty="36" spin_dir="185.009" spin_rate="1349.486"  cc="" mt=""/><pitch des="Called Strike" id="499" type="S" tfs="214318" tfs_zulu="2012-05-26T01:43:18Z" x="145.92" y="145.06" on_1b="458628" sv_id="120525_214319" start_speed="92.6" end_speed="85.6" sz_top="3.9" sz_bot="1.85" pfx_x="-7.3" pfx_z="6.43" px="-1.413" pz="2.441" x0="-2.228" y0="50.0" z0="5.588" vx0="4.729" vy0="-135.58" vz0="-4.688" ax="-13.645" ay="28.661" az="-20.095" break_y="23.8" break_angle="31.0" break_length="5.3" pitch_type="FF" type_confidence=".890" zone="13" nasty="23" spin_dir="228.483" spin_rate="1949.994"  cc="" mt=""/><pitch des="Swinging Strike" id="500" type="S" tfs="214359" tfs_zulu="2012-05-26T01:43:59Z" x="150.21" y="140.74" on_1b="458628" sv_id="120525_214346" start_speed="94.5" end_speed="87.7" sz_top="3.66" sz_bot="1.73" pfx_x="-6.58" pfx_z="6.32" px="-1.603" pz="2.748" x0="-2.175" y0="50.0" z0="5.824" vx0="3.914" vy0="-138.422" vz0="-4.838" ax="-12.873" ay="28.403" az="-19.733" break_y="23.8" break_angle="30.3" break_length="5.0" pitch_type="FF" type_confidence=".904" zone="11" nasty="20" spin_dir="225.977" spin_rate="1876.317"  cc="" mt=""/></atbat><action b="0" s="1" o="2" des="With Alfonso Soriano batting, Juan Cruz picks off Joe Mather at 1st on throw to Casey McGehee.  " event="Pickoff 1B" tfs="214523" tfs_zulu="2012-05-26T01:45:23Z" player="458628" pitch="1"/><atbat num="62" b="0" s="2" o="2" start_tfs="214403" start_tfs_zulu="2012-05-26T01:44:03Z" batter="150093" stand="R" b_height="6-1" pitcher="407297" p_throws="R" des="Alfonso Soriano singles on a line drive to center fielder Andrew McCutchen.  " event="Single"><pitch des="Called Strike" id="504" type="S" tfs="214432" tfs_zulu="2012-05-26T01:44:32Z" x="122.75" y="148.51" on_1b="458628" sv_id="120525_214434" start_speed="80.3" end_speed="74.7" sz_top="3.39" sz_bot="1.61" pfx_x="8.48" pfx_z="1.73" px="-0.747" pz="2.465" x0="-2.593" y0="50.0" z0="5.648" vx0="1.734" vy0="-117.788" vz0="-1.05" ax="11.957" ay="21.525" az="-29.653" break_y="23.9" break_angle="-22.3" break_length="9.3" pitch_type="SL" type_confidence=".892" zone="13" nasty="71" spin_dir="101.906" spin_rate="1505.109"  cc="" mt=""/><po des="Pickoff Attempt 1B"/><po des="Pickoff 1B"/><runner id="458628" start="1B" end="" event="Pickoff 1B"/><pitch des="Foul" id="509" type="S" tfs="214538" tfs_zulu="2012-05-26T01:45:38Z" x="92.70" y="148.51" sv_id="120525_214539" start_speed="94.8" end_speed="87.2" sz_top="3.39" sz_bot="1.61" pfx_x="-4.87" pfx_z="10.11" px="0.157" pz="2.446" x0="-1.983" y0="50.0" z0="5.71" vx0="7.593" vy0="-138.74" vz0="-6.673" ax="-9.489" ay="31.278" az="-12.404" break_y="23.8" break_angle="29.4" break_length="3.3" pitch_type="FF" type_confidence=".919" zone="5" nasty="23" spin_dir="205.638" spin_rate="2293.112"  cc="" mt=""/><pitch des="In play, no out" id="510" type="X" tfs="214626" tfs_zulu="2012-05-26T01:46:26Z" x="105.58" y="139.02" sv_id="120525_214612" start_speed="93.2" end_speed="85.7" sz_top="3.39" sz_bot="1.61" pfx_x="-5.0" pfx_z="8.19" px="-0.174" pz="2.738" x0="-2.481" y0="50.0" z0="5.653" vx0="7.955" vy0="-136.322" vz0="-4.74" ax="-9.402" ay="30.131" az="-16.698" break_y="23.8" break_angle="23.5" break_length="4.2" pitch_type="FF" type_confidence=".899" zone="5" nasty="29" spin_dir="211.278" spin_rate="1927.124"  cc="Juan Cruz had Alfonso Soriano down 0-2 but could not put him away." mt=""/><runner id="150093" start="" end="1B" event="Single"/></atbat><action b="0" s="0" o="2" des="Offensive Substitution: Pinch runner Tony Campana replaces Alfonso Soriano.  " event="Offensive sub" tfs="214656" tfs_zulu="2012-05-26T01:46:56Z" player="542999" pitch="0"/><action b="1" s="1" o="2" des="With Adrian Cardenas batting, Tony Campana steals (13) 2nd base.  " event="Stolen Base 2B" tfs="214802" tfs_zulu="2012-05-26T01:48:02Z" player="542999" pitch="2"/><atbat num="63" b="1" s="2" o="3" start_tfs="214632" start_tfs_zulu="2012-05-26T01:46:32Z" batter="502133" stand="L" b_height="6-0" pitcher="407297" p_throws="R" des="Adrian Cardenas grounds out, second baseman Neil Walker to first baseman Casey McGehee.  " event="Groundout"><runner id="150093" start="1B" end="" event="Groundout"/><runner id="542999" start="" end="1B" event="Groundout"/><pitch des="Called Strike" id="516" type="S" tfs="214707" tfs_zulu="2012-05-26T01:47:07Z" x="139.06" y="147.65" on_1b="542999" sv_id="120525_214708" start_speed="93.5" end_speed="86.4" sz_top="3.47" sz_bot="1.69" pfx_x="-8.19" pfx_z="5.69" px="-1.109" pz="2.387" x0="-2.339" y0="50.0" z0="5.663" vx0="6.207" vy0="-136.915" vz0="-4.934" ax="-15.584" ay="29.535" az="-21.28" break_y="23.8" break_angle="32.6" break_length="5.6" pitch_type="FF" type_confidence=".896" zone="13" nasty="67" spin_dir="235.044" spin_rate="2014.789"  cc="" mt=""/><pitch des="Pitchout" id="517" type="B" tfs="214747" tfs_zulu="2012-05-26T01:47:47Z" x="191.42" y="125.20" on_1b="542999" sv_id="120525_214748" start_speed="90.0" end_speed="83.2" sz_top="3.36" sz_bot="1.58" pfx_x="-6.04" pfx_z="8.31" px="-3.032" pz="3.313" x0="-2.729" y0="50.0" z0="5.727" vx0="1.257" vy0="-132.002" vz0="-2.965" ax="-10.687" ay="27.231" az="-17.393" break_y="23.8" break_angle="30.1" break_length="4.8" pitch_type="PO" type_confidence=".000" zone="11" nasty="0" spin_dir="215.867" spin_rate="2004.664"  cc="" mt=""/><runner id="542999" start="1B" end="2B" event="Stolen Base 2B"/><pitch des="Called Strike" id="521" type="S" tfs="214831" tfs_zulu="2012-05-26T01:48:31Z" x="131.33" y="155.42" on_2b="542999" sv_id="120525_214833" start_speed="79.8" end_speed="74.3" sz_top="3.36" sz_bot="1.58" pfx_x="12.0" pfx_z="-0.86" px="-0.966" pz="2.05" x0="-2.771" y0="50.0" z0="5.603" vx0="0.568" vy0="-117.086" vz0="-1.012" ax="16.661" ay="22.056" az="-33.298" break_y="23.9" break_angle="-26.5" break_length="10.9" pitch_type="SL" type_confidence=".904" zone="13" nasty="51" spin_dir="86.140" spin_rate="2069.114"  cc="" mt=""/><pitch des="In play, out(s)" id="522" type="X" tfs="214931" tfs_zulu="2012-05-26T01:49:31Z" x="125.32" y="144.20" on_2b="542999" sv_id="120525_214855" start_speed="93.7" end_speed="86.4" sz_top="3.36" sz_bot="1.58" pfx_x="-3.84" pfx_z="10.16" px="-0.821" pz="2.418" x0="-2.126" y0="50.0" z0="5.791" vx0="4.891" vy0="-137.12" vz0="-6.799" ax="-7.331" ay="29.522" az="-12.693" break_y="23.8" break_angle="24.0" break_length="3.3" pitch_type="FF" type_confidence=".913" zone="13" nasty="46" spin_dir="200.621" spin_rate="2202.278"  cc="" mt=""/><runner id="542999" start="2B" end="" event="Groundout"/></atbat></top><bottom><action b="0" s="0" o="0" des="Defensive switch from center field to left field for Joe Mather.  " event="Defensive Switch" tfs="215044" tfs_zulu="2012-05-26T01:50:44Z" player="458628" pitch="4"/><action b="0" s="0" o="0" des="Tony Campana remains in the game as the center fielder.  " event="Defensive Switch" tfs="215044" tfs_zulu="2012-05-26T01:50:44Z" player="542999" pitch="4"/><atbat num="64" b="1" s="3" o="1" start_tfs="215143" start_tfs_zulu="2012-05-26T01:51:43Z" batter="476883" stand="L" b_height="6-3" pitcher="133225" p_throws="R" des="Pedro Alvarez strikes out swinging.  " event="Strikeout"><pitch des="Foul Tip" id="532" type="S" tfs="215133" tfs_zulu="2012-05-26T01:51:33Z" x="127.04" y="138.15" sv_id="120525_215134" start_speed="86.5" end_speed="80.4" sz_top="3.45" sz_bot="1.68" pfx_x="-5.49" pfx_z="8.05" px="-0.809" pz="2.911" x0="-1.934" y0="50.0" z0="6.079" vx0="4.616" vy0="-126.663" vz0="-4.19" ax="-8.996" ay="23.568" az="-18.899" break_y="23.8" break_angle="22.6" break_length="5.3" pitch_type="FF" type_confidence=".754" zone="11" nasty="69" spin_dir="214.123" spin_rate="1836.745"  cc="" mt=""/><pitch des="Ball" id="533" type="B" tfs="215154" tfs_zulu="2012-05-26T01:51:54Z" x="148.50" y="175.28" sv_id="120525_215155" start_speed="88.6" end_speed="82.0" sz_top="3.45" sz_bot="1.68" pfx_x="-6.58" pfx_z="7.94" px="-1.57" pz="1.103" x0="-1.918" y0="50.0" z0="5.97" vx0="3.082" vy0="-129.655" vz0="-8.839" ax="-11.21" ay="26.807" az="-18.571" break_y="23.8" break_angle="27.5" break_length="5.5" pitch_type="FT" type_confidence=".903" zone="13" nasty="31" spin_dir="219.490" spin_rate="1972.366"  cc="" mt=""/><pitch des="Foul Tip" id="534" type="S" tfs="215213" tfs_zulu="2012-05-26T01:52:13Z" x="98.71" y="140.74" sv_id="120525_215215" start_speed="84.5" end_speed="79.3" sz_top="3.45" sz_bot="1.68" pfx_x="2.26" pfx_z="2.38" px="0.094" pz="2.796" x0="-1.795" y0="50.0" z0="6.275" vx0="3.924" vy0="-123.834" vz0="-2.805" ax="3.57" ay="20.938" az="-28.342" break_y="23.9" break_angle="-8.2" break_length="7.4" pitch_type="SL" type_confidence=".905" zone="5" nasty="24" spin_dir="137.028" spin_rate="613.576"  cc="" mt=""/><pitch des="Swinging Strike" id="535" type="S" tfs="215248" tfs_zulu="2012-05-26T01:52:48Z" x="88.41" y="170.96" sv_id="120525_215237" start_speed="85.1" end_speed="79.6" sz_top="3.45" sz_bot="1.68" pfx_x="1.6" pfx_z="3.05" px="0.417" pz="1.363" x0="-1.643" y0="50.0" z0="6.157" vx0="4.574" vy0="-124.545" vz0="-6.319" ax="2.541" ay="22.65" az="-27.259" break_y="23.9" break_angle="-6.6" break_length="7.3" pitch_type="SL" type_confidence=".904" zone="14" nasty="45" spin_dir="152.663" spin_rate="644.518"  cc="" mt=""/></atbat><atbat num="65" b="0" s="2" o="1" start_tfs="215251" start_tfs_zulu="2012-05-26T01:52:51Z" batter="435522" stand="L" b_height="6-3" pitcher="133225" p_throws="R" des="Neil Walker doubles (7) on a fly ball to right fielder David DeJesus.  " event="Double"><pitch des="Swinging Strike" id="539" type="S" tfs="215315" tfs_zulu="2012-05-26T01:53:15Z" x="94.42" y="175.28" sv_id="120525_215316" start_speed="82.6" end_speed="77.1" sz_top="3.6" sz_bot="1.7" pfx_x="2.27" pfx_z="4.72" px="0.119" pz="1.329" x0="-1.845" y0="50.0" z0="6.196" vx0="3.996" vy0="-120.978" vz0="-6.426" ax="3.391" ay="22.145" az="-25.058" break_y="23.9" break_angle="-8.7" break_length="7.2" pitch_type="SL" type_confidence=".904" zone="14" nasty="67" spin_dir="154.522" spin_rate="945.298"  cc="" mt=""/><pitch des="Foul" id="540" type="S" tfs="215335" tfs_zulu="2012-05-26T01:53:35Z" x="143.35" y="130.38" sv_id="120525_215337" start_speed="90.1" end_speed="82.7" sz_top="3.6" sz_bot="1.7" pfx_x="-6.28" pfx_z="8.68" px="-1.331" pz="3.089" x0="-1.69" y0="50.0" z0="6.143" vx0="3.055" vy0="-132.057" vz0="-4.71" ax="-11.032" ay="29.347" az="-16.842" break_y="23.8" break_angle="30.1" break_length="4.8" pitch_type="FT" type_confidence=".891" zone="11" nasty="30" spin_dir="215.735" spin_rate="2075.096"  cc="" mt=""/><pitch des="In play, no out" id="541" type="X" tfs="215423" tfs_zulu="2012-05-26T01:54:23Z" x="83.26" y="139.02" sv_id="120525_215405" start_speed="90.8" end_speed="83.5" sz_top="3.6" sz_bot="1.7" pfx_x="-3.52" pfx_z="13.73" px="0.506" pz="2.744" x0="-1.448" y0="50.0" z0="6.092" vx0="6.324" vy0="-132.85" vz0="-7.336" ax="-6.292" ay="28.625" az="-7.569" break_y="23.8" break_angle="28.5" break_length="2.4" pitch_type="FF" type_confidence=".894" zone="6" nasty="40" spin_dir="194.343" spin_rate="2773.441"  cc="Ryan Dempster had Neil Walker down 0-2 but could not put him away." mt=""/><runner id="435522" start="" end="2B" event="Double"/></atbat><action b="0" s="0" o="1" des="Offensive Substitution: Pinch hitter Garrett Jones replaces Juan Cruz.  " event="Offensive sub" tfs="215734" tfs_zulu="2012-05-26T01:57:34Z" player="434540" pitch="0"/><action b="0" s="0" o="1" des="Pitcher Change: James Russell replaces Ryan Dempster, batting 9th.  " event="Pitching Substitution" tfs="215751" tfs_zulu="2012-05-26T01:57:51Z" player="460701" pitch="0"/><action b="0" s="0" o="1" des="Coaching visit to mound.  " event="Game Advisory" tfs="215811" tfs_zulu="2012-05-26T01:58:11Z" player="434540" pitch="0"/><atbat num="66" b="0" s="0" o="2" start_tfs="" start_tfs_zulu="" batter="434540" stand="L" b_height="6-4" pitcher="460701" p_throws="L" des="Garrett Jones grounds out, shortstop Starlin Castro to first baseman Bryan LaHair.    Neil Walker to 3rd.  " event="Groundout"><pitch des="In play, out(s)" id="550" type="X" tfs="215854" tfs_zulu="2012-05-26T01:58:54Z" x="140.77" y="145.92" on_2b="435522" sv_id="120525_215832" start_speed="80.0" end_speed="74.9" sz_top="3.74" sz_bot="1.67" pfx_x="-0.76" pfx_z="2.35" px="-1.121" pz="2.389" x0="1.519" y0="50.0" z0="6.551" vx0="-5.901" vy0="-117.151" vz0="-3.462" ax="-1.066" ay="20.159" az="-28.804" break_y="23.9" break_angle="3.8" break_length="8.5" pitch_type="SL" type_confidence=".877" zone="13" nasty="78" spin_dir="197.552" spin_rate="437.718"  cc="" mt=""/><runner id="435522" start="2B" end="3B" event="Groundout"/></atbat><atbat num="67" b="0" s="1" o="3" start_tfs="215858" start_tfs_zulu="2012-05-26T01:58:58Z" batter="150148" stand="R" b_height="6-2" pitcher="460701" p_throws="L" des="Rod Barajas pops out to first baseman Bryan LaHair in foul territory.  " event="Pop Out"><pitch des="Called Strike" id="555" type="S" tfs="215917" tfs_zulu="2012-05-26T01:59:17Z" x="97.00" y="137.29" on_3b="435522" sv_id="120525_215918" start_speed="90.7" end_speed="83.2" sz_top="3.45" sz_bot="1.63" pfx_x="8.49" pfx_z="12.21" px="0.091" pz="2.745" x0="1.473" y0="50.0" z0="6.328" vx0="-6.494" vy0="-132.645" vz0="-7.373" ax="15.068" ay="29.348" az="-10.43" break_y="23.8" break_angle="-48.6" break_length="4.2" pitch_type="FT" type_confidence=".934" zone="5" nasty="35" spin_dir="145.280" spin_rate="2893.428"  cc="" mt=""/><pitch des="In play, out(s)" id="556" type="X" tfs="215954" tfs_zulu="2012-05-26T01:59:54Z" x="109.87" y="161.47" on_3b="435522" sv_id="120525_215939" start_speed="81.0" end_speed="76.1" sz_top="3.45" sz_bot="1.63" pfx_x="0.81" pfx_z="3.21" px="-0.465" pz="1.558" x0="1.439" y0="50.0" z0="6.45" vx0="-4.731" vy0="-118.624" vz0="-5.681" ax="1.176" ay="20.012" az="-27.472" break_y="23.9" break_angle="-1.0" break_length="7.9" pitch_type="SL" type_confidence=".783" zone="13" nasty="51" spin_dir="165.960" spin_rate="592.772"  cc="" mt=""/><runner id="435522" start="3B" end="" event="Pop Out"/></atbat></bottom></inning>