<!--Copyright 2012 MLB Advanced Media, L.P.  Use of any content on this page acknowledges agreement to the terms posted here http://gdx.mlb.com/components/copyright.txt--><inning num="4" away_team="mil" home_team="pit" next="Y"><top><atbat num="32" b="1" s="1" o="0" start_tfs="201516" start_tfs_zulu="2011-08-24T00:15:16Z" batter="460579" stand="L" b_height="6-0" pitcher="456027" p_throws="R" des="Nyjer Morgan singles on a line drive to right fielder Xavier Paul.  " event="Single"><pitch des="Ball" id="246" type="B" tfs="201527" tfs_zulu="2011-08-24T00:15:27Z" x="72.10" y="141.61" sv_id="110823_201539" start_speed="88.7" end_speed="81.7" sz_top="3.01" sz_bot="1.4" pfx_x="-6.92" pfx_z="9.25" px="0.776" pz="2.718" x0="-2.196" y0="50.0" z0="6.277" vx0="9.906" vy0="-129.625" vz0="-5.909" ax="-11.768" ay="27.178" az="-16.373" break_y="23.8" break_angle="29.0" break_length="4.8" pitch_type="FF" type_confidence=".914" zone="12" nasty="72" spin_dir="216.676" spin_rate="2205.045"  cc="" mt=""/><pitch des="Swinging Strike" id="247" type="S" tfs="201540" tfs_zulu="2011-08-24T00:15:40Z" x="118.45" y="163.19" sv_id="110823_201552" start_speed="77.9" end_speed="73.2" sz_top="3.21" sz_bot="1.54" pfx_x="-8.76" pfx_z="4.09" px="-0.501" pz="1.674" x0="-2.199" y0="50.0" z0="6.34" vx0="6.427" vy0="-113.925" vz0="-4.677" ax="-11.691" ay="17.875" az="-26.636" break_y="23.9" break_angle="21.6" break_length="8.9" pitch_type="CH" type_confidence=".900" zone="7" nasty="47" spin_dir="244.653" spin_rate="1647.383"  cc="" mt=""/><pitch des="In play, no out" id="248" type="X" tfs="201557" tfs_zulu="2011-08-24T00:15:57Z" x="125.32" y="145.06" sv_id="110823_201608" start_speed="78.1" end_speed="72.9" sz_top="3.21" sz_bot="1.54" pfx_x="-9.55" pfx_z="3.03" px="-0.72" pz="2.367" x0="-2.169" y0="50.0" z0="6.6" vx0="6.094" vy0="-114.311" vz0="-3.398" ax="-12.747" ay="19.283" az="-28.051" break_y="23.9" break_angle="22.5" break_length="9.4" pitch_type="CH" type_confidence=".900" zone="13" nasty="40" spin_dir="252.076" spin_rate="1700.311"  cc="" mt=""/><runner id="460579" start="" end="1B" event="Single"/></atbat><atbat num="33" b="0" s="1" o="0" start_tfs="201626" start_tfs_zulu="2011-08-24T00:16:26Z" batter="460075" stand="R" b_height="6-1" pitcher="456027" p_throws="R" des="Ryan Braun doubles (31) on a fly ball to center fielder Andrew McCutchen.    Nyjer Morgan to 3rd.  " event="Double"><pitch des="Called Strike" id="252" type="S" tfs="201639" tfs_zulu="2011-08-24T00:16:39Z" x="78.97" y="147.65" on_1b="460579" sv_id="110823_201651" start_speed="77.6" end_speed="70.8" sz_top="3.65" sz_bot="1.63" pfx_x="1.95" pfx_z="2.14" px="0.649" pz="2.501" x0="-2.301" y0="50.0" z0="6.744" vx0="5.995" vy0="-113.616" vz0="-2.825" ax="2.497" ay="25.0" az="-29.363" break_y="23.7" break_angle="-7.0" break_length="9.6" pitch_type="SL" type_confidence=".894" zone="6" nasty="69" spin_dir="138.386" spin_rate="480.106"  cc="" mt=""/><pitch des="In play, no out" id="253" type="X" tfs="201709" tfs_zulu="2011-08-24T00:17:09Z" x="136.48" y="147.65" on_1b="460579" sv_id="110823_201720" start_speed="90.9" end_speed="83.7" sz_top="3.43" sz_bot="1.63" pfx_x="-8.95" pfx_z="6.36" px="-1.085" pz="2.355" x0="-2.619" y0="50.0" z0="6.069" vx0="7.079" vy0="-133.057" vz0="-5.8" ax="-16.02" ay="29.114" az="-20.716" break_y="23.8" break_angle="33.5" break_length="6.0" pitch_type="FT" type_confidence=".907" zone="13" nasty="55" spin_dir="234.426" spin_rate="2147.529"  cc="" mt=""/><runner id="460579" start="1B" end="3B" event="Double"/><runner id="460075" start="" end="2B" event="Double"/></atbat><atbat num="34" b="4" s="0" o="0" start_tfs="201749" start_tfs_zulu="2011-08-24T00:17:49Z" batter="425902" stand="L" b_height="5-11" pitcher="456027" p_throws="R" des="Ross Ohlendorf intentionally walks Prince Fielder.  " event="Intent Walk"><pitch des="Intent Ball" id="258" type="B" tfs="201801" tfs_zulu="2011-08-24T00:18:01Z" x="188.84" y="80.30" on_2b="460075" on_3b="460579" sv_id="110823_201813" start_speed="64.6" end_speed="59.5" sz_top="3.31" sz_bot="1.64" pfx_x="-2.54" pfx_z="8.5" px="-6.341" pz="5.207" x0="-3.231" y0="50.0" z0="7.293" vx0="-5.175" vy0="-94.57" vz0="2.684" ax="-2.287" ay="15.334" az="-24.453" break_y="23.8" break_angle="7.3" break_length="10.9" pitch_type="IN" type_confidence=".000" zone="11" nasty="0" spin_dir="196.498" spin_rate="1235.334"  cc="" mt=""/><pitch des="Intent Ball" id="259" type="B" tfs="201812" tfs_zulu="2011-08-24T00:18:12Z" x="192.27" y="71.67" on_2b="460075" on_3b="460579" sv_id="110823_201824" start_speed="71.0" end_speed="64.9" sz_top="3.31" sz_bot="1.64" pfx_x="-3.02" pfx_z="6.71" px="-6.277" pz="5.635" x0="-3.27" y0="50.0" z0="7.144" vx0="-5.34" vy0="-103.892" vz0="3.002" ax="-3.265" ay="19.13" az="-24.848" break_y="23.7" break_angle="9.8" break_length="9.3" pitch_type="IN" type_confidence=".000" zone="11" nasty="0" spin_dir="204.020" spin_rate="1120.027"  cc="" mt=""/><pitch des="Intent Ball" id="260" type="B" tfs="201822" tfs_zulu="2011-08-24T00:18:22Z" x="193.99" y="88.07" on_2b="460075" on_3b="460579" sv_id="110823_201834" start_speed="71.5" end_speed="66.3" sz_top="3.31" sz_bot="1.64" pfx_x="-4.33" pfx_z="7.29" px="-6.089" pz="4.928" x0="-3.292" y0="50.0" z0="7.076" vx0="-4.625" vy0="-104.775" vz0="1.345" ax="-4.825" ay="17.337" az="-23.979" break_y="23.8" break_angle="13.1" break_length="8.9" pitch_type="IN" type_confidence=".000" zone="11" nasty="0" spin_dir="210.487" spin_rate="1316.805"  cc="" mt=""/><pitch des="Intent Ball" id="261" type="B" tfs="201833" tfs_zulu="2011-08-24T00:18:33Z" x="193.99" y="68.21" on_2b="460075" on_3b="460579" sv_id="110823_201845" start_speed="69.9" end_speed="64.9" sz_top="3.31" sz_bot="1.64" pfx_x="-5.71" pfx_z="6.71" px="-6.064" pz="6.044" x0="-3.284" y0="50.0" z0="7.272" vx0="-4.131" vy0="-102.433" vz0="3.661" ax="-6.096" ay="16.05" az="-24.927" break_y="23.8" break_angle="15.4" break_length="9.6" pitch_type="IN" type_confidence=".000" zone="11" nasty="0" spin_dir="220.069" spin_rate="1341.253"  cc="" mt=""/><runner id="425902" start="" end="1B" event="Intent Walk"/></atbat><atbat num="35" b="1" s="0" o="1" start_tfs="201850" start_tfs_zulu="2011-08-24T00:18:50Z" batter="431171" stand="R" b_height="6-1" pitcher="456027" p_throws="R" des="Casey McGehee flies out to right fielder Xavier Paul on the infield fly rule.  " event="Flyout"><pitch des="Ball" id="265" type="B" tfs="201913" tfs_zulu="2011-08-24T00:19:13Z" x="63.52" y="172.69" on_1b="425902" on_2b="460075" on_3b="460579" sv_id="110823_201925" start_speed="79.1" end_speed="72.6" sz_top="3.22" sz_bot="1.53" pfx_x="2.23" pfx_z="0.0" px="1.105" pz="1.406" x0="-2.214" y0="50.0" z0="6.52" vx0="6.868" vy0="-115.675" vz0="-4.509" ax="2.961" ay="25.21" az="-32.104" break_y="23.8" break_angle="-7.3" break_length="10.2" pitch_type="SL" type_confidence=".878" zone="14" nasty="92" spin_dir="91.354" spin_rate="371.469"  cc="" mt=""/><pitch des="In play, out(s)" id="266" type="X" tfs="201934" tfs_zulu="2011-08-24T00:19:34Z" x="125.32" y="131.24" on_1b="425902" on_2b="460075" on_3b="460579" sv_id="110823_201945" start_speed="90.8" end_speed="84.0" sz_top="3.78" sz_bot="1.74" pfx_x="-7.83" pfx_z="4.23" px="-0.704" pz="3.064" x0="-2.525" y0="50.0" z0="6.245" vx0="7.464" vy0="-132.86" vz0="-3.699" ax="-14.071" ay="27.13" az="-24.508" break_y="23.8" break_angle="26.6" break_length="6.4" pitch_type="FF" type_confidence=".932" zone="4" nasty="46" spin_dir="241.417" spin_rate="1749.735"  cc="" mt=""/></atbat><atbat num="36" b="0" s="1" o="3" start_tfs="202019" start_tfs_zulu="2011-08-24T00:20:19Z" batter="435358" stand="R" b_height="5-11" pitcher="456027" p_throws="R" des="Yuniesky Betancourt grounds into double play, second baseman Neil Walker to shortstop Ronny Cedeno to first baseman Garrett Jones.    Prince Fielder out at 2nd.  " event="Grounded Into DP"><pitch des="Called Strike" id="270" type="S" tfs="202019" tfs_zulu="2011-08-24T00:20:19Z" x="123.61" y="135.56" on_1b="425902" on_2b="460075" on_3b="460579" sv_id="110823_202031" start_speed="80.0" end_speed="74.4" sz_top="3.3" sz_bot="1.53" pfx_x="-8.38" pfx_z="5.29" px="-0.665" pz="2.779" x0="-2.274" y0="50.0" z0="6.559" vx0="6.259" vy0="-117.058" vz0="-3.438" ax="-11.716" ay="20.477" az="-24.699" break_y="23.9" break_angle="22.9" break_length="7.9" pitch_type="CH" type_confidence=".902" zone="1" nasty="67" spin_dir="237.461" spin_rate="1722.414"  cc="" mt=""/><pitch des="In play, out(s)" id="271" type="X" tfs="202037" tfs_zulu="2011-08-24T00:20:37Z" x="63.52" y="152.83" on_1b="425902" on_2b="460075" on_3b="460579" sv_id="110823_202049" start_speed="81.1" end_speed="75.7" sz_top="3.33" sz_bot="1.5" pfx_x="2.04" pfx_z="-0.57" px="1.173" pz="2.232" x0="-2.21" y0="50.0" z0="6.512" vx0="7.317" vy0="-118.635" vz0="-3.034" ax="2.926" ay="21.582" az="-32.921" break_y="23.9" break_angle="-6.9" break_length="9.5" pitch_type="SL" type_confidence=".883" zone="14" nasty="46" spin_dir="75.678" spin_rate="369.296"  cc="" mt=""/><runner id="425902" start="1B" end="" event="Grounded Into DP"/><runner id="460075" start="2B" end="" event="Grounded Into DP"/><runner id="460579" start="3B" end="" event="Grounded Into DP"/></atbat></top><bottom><atbat num="37" b="2" s="1" o="1" start_tfs="202310" start_tfs_zulu="2011-08-24T00:23:10Z" batter="425491" stand="L" b_height="6-1" pitcher="462136" p_throws="R" des="Ryan Doumit flies out to center fielder Nyjer Morgan.  " event="Flyout"><pitch des="Ball" id="278" type="B" tfs="202313" tfs_zulu="2011-08-24T00:23:13Z" x="175.97" y="91.53" sv_id="110823_202325" start_speed="75.9" end_speed="70.3" sz_top="3.24" sz_bot="1.62" pfx_x="6.3" pfx_z="-5.95" px="-2.191" pz="4.814" x0="-2.454" y0="50.0" z0="6.149" vx0="-1.22" vy0="-111.187" vz0="6.066" ax="7.909" ay="19.293" az="-39.576" break_y="23.8" break_angle="-11.3" break_length="12.7" pitch_type="CU" type_confidence=".891" zone="11" nasty="69" spin_dir="46.896" spin_rate="1413.431"  cc="" mt=""/><pitch des="Foul" id="279" type="S" tfs="202328" tfs_zulu="2011-08-24T00:23:28Z" x="110.73" y="155.42" sv_id="110823_202340" start_speed="78.0" end_speed="71.9" sz_top="3.21" sz_bot="1.62" pfx_x="-7.88" pfx_z="5.52" px="-0.295" pz="2.123" x0="-1.896" y0="50.0" z0="5.594" vx0="5.906" vy0="-114.156" vz0="-2.298" ax="-10.366" ay="21.525" az="-24.833" break_y="23.8" break_angle="20.3" break_length="8.3" pitch_type="CH" type_confidence=".901" zone="7" nasty="30" spin_dir="234.694" spin_rate="1614.285"  cc="" mt=""/><pitch des="Ball" id="280" type="B" tfs="202348" tfs_zulu="2011-08-24T00:23:48Z" x="117.60" y="157.15" sv_id="110823_202359" start_speed="90.5" end_speed="83.4" sz_top="3.22" sz_bot="1.52" pfx_x="-4.66" pfx_z="10.57" px="-0.568" pz="2.065" x0="-1.549" y0="50.0" z0="5.611" vx0="4.149" vy0="-132.473" vz0="-6.735" ax="-8.283" ay="28.06" az="-13.305" break_y="23.8" break_angle="26.8" break_length="3.8" pitch_type="FF" type_confidence=".918" zone="7" nasty="46" spin_dir="203.699" spin_rate="2256.779"  cc="" mt=""/><pitch des="In play, out(s)" id="281" type="X" tfs="202403" tfs_zulu="2011-08-24T00:24:03Z" x="134.76" y="148.51" sv_id="110823_202415" start_speed="78.8" end_speed="72.8" sz_top="3.21" sz_bot="1.62" pfx_x="-7.4" pfx_z="6.63" px="-1.008" pz="2.237" x0="-2.055" y0="50.0" z0="5.599" vx0="4.581" vy0="-115.524" vz0="-2.591" ax="-9.997" ay="21.669" az="-23.141" break_y="23.8" break_angle="21.3" break_length="7.6" pitch_type="CH" type_confidence=".895" zone="13" nasty="49" spin_dir="227.899" spin_rate="1692.039"  cc="" mt=""/></atbat><atbat num="38" b="1" s="3" o="2" start_tfs="202433" start_tfs_zulu="2011-08-24T00:24:33Z" batter="435522" stand="L" b_height="6-3" pitcher="462136" p_throws="R" des="Neil Walker strikes out swinging.  " event="Strikeout"><pitch des="Called Strike" id="285" type="S" tfs="202441" tfs_zulu="2011-08-24T00:24:41Z" x="115.02" y="144.20" sv_id="110823_202452" start_speed="79.9" end_speed="73.4" sz_top="3.62" sz_bot="1.82" pfx_x="5.87" pfx_z="-3.56" px="-0.489" pz="2.576" x0="-2.226" y0="50.0" z0="5.686" vx0="2.245" vy0="-117.13" vz0="0.88" ax="8.059" ay="24.604" az="-36.985" break_y="23.8" break_angle="-12.9" break_length="11.2" pitch_type="CU" type_confidence=".905" zone="4" nasty="75" spin_dir="59.163" spin_rate="1162.533"  cc="" mt=""/><pitch des="Ball" id="286" type="B" tfs="202456" tfs_zulu="2011-08-24T00:24:56Z" x="78.11" y="165.78" sv_id="110823_202507" start_speed="91.0" end_speed="83.3" sz_top="3.84" sz_bot="1.82" pfx_x="-3.77" pfx_z="12.7" px="0.714" pz="1.757" x0="-1.226" y0="50.0" z0="5.566" vx0="6.369" vy0="-133.086" vz0="-8.182" ax="-6.73" ay="30.117" az="-9.448" break_y="23.8" break_angle="25.3" break_length="2.8" pitch_type="FF" type_confidence=".926" zone="14" nasty="58" spin_dir="196.494" spin_rate="2583.728"  cc="" mt=""/><pitch des="Foul" id="287" type="S" tfs="202512" tfs_zulu="2011-08-24T00:25:12Z" x="139.91" y="125.20" sv_id="110823_202524" start_speed="79.2" end_speed="73.1" sz_top="3.47" sz_bot="1.82" pfx_x="-7.76" pfx_z="6.7" px="-1.155" pz="3.282" x0="-2.147" y0="50.0" z0="5.776" vx0="4.586" vy0="-116.091" vz0="-0.709" ax="-10.598" ay="21.709" az="-22.952" break_y="23.8" break_angle="23.0" break_length="7.5" pitch_type="CH" type_confidence=".893" zone="11" nasty="57" spin_dir="228.971" spin_rate="1755.644"  cc="" mt=""/><pitch des="Swinging Strike" id="288" type="S" tfs="202539" tfs_zulu="2011-08-24T00:25:39Z" x="62.66" y="160.60" sv_id="110823_202550" start_speed="81.2" end_speed="75.4" sz_top="3.47" sz_bot="1.82" pfx_x="10.51" pfx_z="-4.34" px="1.253" pz="1.973" x0="-2.007" y0="50.0" z0="5.598" vx0="4.444" vy0="-118.955" vz0="-0.328" ax="14.981" ay="23.891" az="-38.287" break_y="23.8" break_angle="-22.3" break_length="11.8" pitch_type="CU" type_confidence=".910" zone="14" nasty="51" spin_dir="67.802" spin_rate="1973.348"  cc="" mt=""/></atbat><atbat num="39" b="2" s="1" o="3" start_tfs="202603" start_tfs_zulu="2011-08-24T00:26:03Z" batter="434540" stand="L" b_height="6-4" pitcher="462136" p_throws="R" des="Garrett Jones flies out to center fielder Nyjer Morgan.  " event="Flyout"><pitch des="Ball" id="292" type="B" tfs="202610" tfs_zulu="2011-08-24T00:26:10Z" x="139.06" y="105.34" sv_id="110823_202622" start_speed="78.3" end_speed="71.7" sz_top="3.79" sz_bot="1.68" pfx_x="-6.16" pfx_z="4.28" px="-1.233" pz="4.147" x0="-2.234" y0="50.0" z0="5.819" vx0="4.067" vy0="-114.758" vz0="2.076" ax="-8.163" ay="22.63" az="-26.438" break_y="23.8" break_angle="15.8" break_length="8.3" pitch_type="CH" type_confidence=".892" zone="11" nasty="85" spin_dir="234.904" spin_rate="1261.275"  cc="" mt=""/><pitch des="Called Strike" id="293" type="S" tfs="202626" tfs_zulu="2011-08-24T00:26:26Z" x="125.32" y="164.06" sv_id="110823_202638" start_speed="90.6" end_speed="82.8" sz_top="3.71" sz_bot="1.68" pfx_x="-5.44" pfx_z="11.84" px="-0.686" pz="1.691" x0="-1.697" y0="50.0" z0="5.631" vx0="4.477" vy0="-132.562" vz0="-8.12" ax="-9.599" ay="30.765" az="-11.22" break_y="23.7" break_angle="33.3" break_length="3.6" pitch_type="FF" type_confidence=".919" zone="7" nasty="61" spin_dir="204.611" spin_rate="2522.416"  cc="" mt=""/><pitch des="Ball" id="294" type="B" tfs="202643" tfs_zulu="2011-08-24T00:26:43Z" x="127.04" y="134.70" sv_id="110823_202655" start_speed="80.5" end_speed="74.4" sz_top="3.6" sz_bot="1.69" pfx_x="10.72" pfx_z="-4.32" px="-0.738" pz="3.025" x0="-2.301" y0="50.0" z0="5.717" vx0="0.399" vy0="-117.998" vz0="1.945" ax="15.046" ay="23.311" az="-38.168" break_y="23.8" break_angle="-21.7" break_length="11.8" pitch_type="CU" type_confidence=".910" zone="11" nasty="41" spin_dir="68.278" spin_rate="1991.293"  cc="" mt=""/><pitch des="In play, out(s)" id="295" type="X" tfs="202700" tfs_zulu="2011-08-24T00:27:00Z" x="132.19" y="145.92" sv_id="110823_202712" start_speed="79.7" end_speed="73.9" sz_top="3.59" sz_bot="1.68" pfx_x="-6.57" pfx_z="4.89" px="-1.032" pz="2.335" x0="-2.181" y0="50.0" z0="5.517" vx0="4.626" vy0="-116.778" vz0="-1.866" ax="-9.113" ay="21.212" az="-25.323" break_y="23.8" break_angle="18.0" break_length="7.9" pitch_type="CH" type_confidence=".886" zone="13" nasty="48" spin_dir="233.064" spin_rate="1416.395"  cc="" mt=""/></atbat></bottom></inning>