<!--Copyright 2007 MLB Advanced Media, L.P.--><inning num="3" next="Y"><top><atbat num="22" b="1" s="3" o="1" batter="150090" pitcher="218294" des="D'Angelo Jimenez strikes out swinging.  " stand="L" event="Strikeout"><pitch des="Ball" id="189" type="B" x="163.95" y="163.19" /><pitch des="Called Strike" id="190" type="S" x="97.00" y="156.29" /><pitch des="Foul" id="191" type="S" x="109.87" y="139.02" /><pitch des="Swinging Strike" id="192" type="S" x="140.77" y="163.19" /></atbat><atbat num="23" b="2" s="3" o="2" batter="150071" pitcher="218294" des="Ronnie Belliard strikes out swinging.  " stand="R" event="Strikeout"><pitch des="Ball" id="196" type="B" x="125.32" y="162.33" /><pitch des="Called Strike" id="197" type="S" x="88.41" y="147.65" /><pitch des="Swinging Strike" id="198" type="S" x="97.00" y="144.20" /><pitch des="Ball" id="199" type="B" x="55.79" y="167.51" /><pitch des="Swinging Strike" id="200" type="S" x="100.43" y="155.42" /></atbat><atbat num="24" b="1" s="1" o="3" batter="475582" pitcher="218294" des="Ryan Zimmerman grounds out, shortstop Robert Andino to first baseman Mike Jacobs.  " stand="R" event="Ground Out"><pitch des="Ball" id="204" type="B" x="60.94" y="164.92" /><pitch des="Swinging Strike" id="205" type="S" x="90.99" y="147.65" /><pitch des="In play, out(s)" id="206" type="X" x="97.00" y="151.97" /></atbat></top><bottom><atbat num="25" b="1" s="2" o="0" batter="408234" pitcher="430629" des="Miguel Cabrera singles on a line drive to left fielder Wily Mo Pena.  " stand="R" event="Single"><pitch des="Called Strike" id="211" type="S" x="84.12" y="141.61" /><pitch des="Foul" id="212" type="S" x="92.70" y="131.24" /><pitch des="Ball" id="213" type="B" x="67.81" y="139.02" /><pitch des="In play, no out" id="214" type="X" x="107.30" y="139.88" /><runner id="408234" start="" end="1B" event="Single"/></atbat><atbat num="26" b="2" s="3" o="1" batter="425545" pitcher="430629" des="Josh Willingham called out on strikes.  " stand="R" event="Strikeout"><pitch des="Ball" id="218" type="B" x="67.81" y="156.29" on_1b="408234" /><pitch des="Foul" id="219" type="S" x="80.69" y="145.06" on_1b="408234" /><pitch des="Ball In Dirt" id="220" type="B" x="59.23" y="187.37" on_1b="408234" /><pitch des="Called Strike" id="221" type="S" x="147.64" y="139.88" on_1b="408234" /><pitch des="Called Strike" id="222" type="S" x="139.91" y="155.42" on_1b="408234" /></atbat><atbat num="27" b="0" s="0" o="2" batter="408312" pitcher="430629" des="Mike Jacobs flies out to right fielder Ryan Langerhans.  " stand="L" event="Fly Out"><pitch des="In play, out(s)" id="226" type="X" x="134.76" y="140.74" on_1b="408234" /></atbat><atbat num="28" b="2" s="0" o="2" batter="400018" pitcher="430629" des="Miguel Olivo homers (16) on a fly ball to left field.   Miguel Cabrera scores.  " stand="R" event="Home Run" score="T"><pitch des="Ball" id="230" type="B" x="72.10" y="172.69" on_1b="408234" /><pitch des="Ball" id="231" type="B" x="142.49" y="118.29" on_1b="408234" /><pitch des="In play, run(s)" id="232" type="X" x="118.45" y="143.33" on_1b="408234" /><runner id="408234" start="1B" end="" event="Home Run" score="T" rbi="T" earned="T"/><runner id="400018" start="" end="" event="Home Run" score="T" rbi="T" earned="T"/></atbat><atbat num="29" b="1" s="0" o="2" batter="435180" pitcher="430629" des="Robert Andino singles on a ground ball to left fielder Wily Mo Pena.  " stand="R" event="Single"><pitch des="Ball" id="239" type="B" x="135.62" y="122.61" /><pitch des="In play, no out" id="240" type="X" x="134.76" y="151.97" /><runner id="435180" start="" end="1B" event="Single"/></atbat><atbat num="30" b="1" s="2" o="3" batter="218294" pitcher="430629" des="Byung-Hyun Kim flies out to center fielder Ryan Church.  " stand="R" event="Fly Out"><pitch des="Ball" id="244" type="B" x="108.15" y="120.02" on_1b="435180" /><pitch des="Called Strike" id="245" type="S" x="101.29" y="163.19" on_1b="435180" /><pitch des="Swinging Strike" id="246" type="S" x="131.33" y="138.15" on_1b="435180" /><pitch des="Foul" id="247" type="S" x="86.70" y="143.33" on_1b="435180" /><pitch des="In play, out(s)" id="248" type="X" x="127.90" y="134.70" on_1b="435180" /><runner id="435180" start="1B" end="" event="Fly Out"/></atbat></bottom></inning>